streamlit_image_annotation/__init__.py
streamlit_image_annotation/Classification/__init__.py
streamlit_image_annotation/Classification/frontend/build/asset-manifest.json
streamlit_image_annotation/Classification/frontend/build/bootstrap.min.css
streamlit_image_annotation/Classification/frontend/build/index.html
streamlit_image_annotation/Classification/frontend/build/static/js/main.4f438506.js
streamlit_image_annotation/Classification/frontend/build/static/js/main.4f438506.js.LICENSE.txt
streamlit_image_annotation/Classification/frontend/build/static/js/main.4f438506.js.map
streamlit_image_annotation/Detection/__init__.py
streamlit_image_annotation/Detection/frontend/build/asset-manifest.json
streamlit_image_annotation/Detection/frontend/build/bootstrap.min.css
streamlit_image_annotation/Detection/frontend/build/index.html
streamlit_image_annotation/Detection/frontend/build/static/js/main.e04cd712.js
streamlit_image_annotation/Detection/frontend/build/static/js/main.e04cd712.js.LICENSE.txt
streamlit_image_annotation/Detection/frontend/build/static/js/main.e04cd712.js.map
streamlit_image_annotation/Point/__init__.py
streamlit_image_annotation/Point/frontend/build/asset-manifest.json
streamlit_image_annotation/Point/frontend/build/bootstrap.min.css
streamlit_image_annotation/Point/frontend/build/index.html
streamlit_image_annotation/Point/frontend/build/static/js/main.0089be5c.js
streamlit_image_annotation/Point/frontend/build/static/js/main.0089be5c.js.LICENSE.txt
streamlit_image_annotation/Point/frontend/build/static/js/main.0089be5c.js.map
streamlit_image_annotation-0.7.2.dist-info/licenses/LICENSE
streamlit_image_annotation-0.7.2.dist-info/METADATA
streamlit_image_annotation-0.7.2.dist-info/WHEEL
streamlit_image_annotation-0.7.2.dist-info/top_level.txt
streamlit_image_annotation-0.7.2.dist-info/RECORD
