Metadata-Version: 2.4
Name: streamlit_image_annotation
Version: 0.7.2
Summary: streamlit components for image annotation
Home-page: https://github.com/hirune924/Streamlit-Image-Annotation
Author: hirune924
Project-URL: Homepage, https://github.com/hirune924/Streamlit-Image-Annotation
Keywords: Python,Streamlit,React,JavaScript
Requires-Python: >=3.6
License-File: LICENSE
Requires-Dist: matplotlib>=3.3.4
Requires-Dist: streamlit>=0.63
Dynamic: home-page
Dynamic: license-file
Dynamic: requires-python
